Viona/__init__.py
Viona/api.py
viona-2.1.0.dist-info/METADATA
viona-2.1.0.dist-info/WHEEL
viona-2.1.0.dist-info/entry_points.txt
viona-2.1.0.dist-info/top_level.txt
viona-2.1.0.dist-info/RECORD
