Metadata-Version: 2.4
Name: viona
Version: 2.1.0
Summary: Viona AI modeline erişim sağlayan hızlı, güvenli ve asenkron destekli Python API istemcisi.
Home-page: https://viona.orvixgames.com/app/modul/viona-api-modul.php
Author: Orvix Games
Author-email: destek@orvixgames.com
License: MIT
Project-URL: Documentation, https://viona.orvixgames.com/app/modul/viona-api-modul.php
Project-URL: Homepage, https://viona.orvixgames.com/app/modul/viona-api-modul.php
Keywords: viona ai api orvixgames yapayzeka client python modul
Classifier: Development Status :: 5 - Production/Stable
Classifier: Intended Audience :: Developers
Classifier: Topic :: Software Development :: Libraries :: Python Modules
Classifier: Programming Language :: Python :: 3 :: Only
Classifier: Programming Language :: Python :: 3.8
Classifier: Programming Language :: Python :: 3.9
Classifier: Programming Language :: Python :: 3.10
Classifier: License :: OSI Approved :: MIT License
Classifier: Operating System :: OS Independent
Classifier: Natural Language :: Turkish
Requires-Python: >=3.8
Requires-Dist: requests>=2.25.1
Requires-Dist: aiohttp>=3.8.1
Requires-Dist: httpx>=0.23.0
Requires-Dist: tqdm>=4.65.0
Requires-Dist: python-dotenv>=1.0.0
Dynamic: author
Dynamic: author-email
Dynamic: classifier
Dynamic: description
Dynamic: description-content-type
Dynamic: home-page
Dynamic: keywords
Dynamic: license
Dynamic: project-url
Dynamic: requires-dist
Dynamic: requires-python
Dynamic: summary
